bdata/__init__.py
bdata/asym_fns.py
bdata/bdata.py
bdata/bjoined.py
bdata/bmerged.py
bdata/calc.py
bdata/containers.py
bdata/exceptions.py
bdata/life.py
bdata/version.py
bdata/data/nmr_antenna_data.csv
bdata-6.11.4.dist-info/METADATA
bdata-6.11.4.dist-info/WHEEL
bdata-6.11.4.dist-info/licenses/LICENSE
bdata-6.11.4.dist-info/RECORD
