Metadata-Version: 2.1
Name: bdata
Version: 6.11.4
Summary: β-NMR/β-NQR MUD file reader and asymmetry calculator
Project-URL: Homepage, https://github.com/dfujim/bdata
Project-URL: Bug Tracker, https://github.com/dfujim/bdata/issues
Author-email: Derek Fujimoto <dfujimoto@triumf.ca>
License:                     GNU GENERAL PUBLIC LICENSE
License-File: LICENSE
Classifier: Development Status :: 5 - Production/Stable
Classifier: License :: OSI Approved :: GNU Lesser General Public License v3 (LGPLv3)
Classifier: Operating System :: MacOS
Classifier: Operating System :: Microsoft :: Windows
Classifier: Operating System :: POSIX :: Linux
Classifier: Programming Language :: Python :: 3
Classifier: Programming Language :: Python :: 3.6
Classifier: Programming Language :: Python :: 3.7
Requires-Python: >=3.7
Requires-Dist: iminuit>=2.6.1
Requires-Dist: mud-py>=1.2.14
Requires-Dist: numpy>=1.19
Requires-Dist: pandas>=0.25
Requires-Dist: requests>=2.22.0
Requires-Dist: scipy>=1.2.0
